{
  "packId": "en_es_travel_20",
  "version": "1.0",
  "words": [
    {
      "originalWord": "airport",
      "translation": "aeropuerto",
      "transcription": "[aeɾoˈpweɾto]",
      "exampleSentence": "Voy al aeropuerto."
    },
    {
      "originalWord": "hotel",
      "translation": "hotel",
      "transcription": "[oˈtel]",
      "exampleSentence": "¿Dónde está mi hotel?"
    },
    {
      "originalWord": "ticket",
      "translation": "boleto",
      "transcription": "[boˈleto]",
      "exampleSentence": "Necesito comprar un boleto."
    },
    {
      "originalWord": "passport",
      "translation": "pasaporte",
      "transcription": "[pasaˈpoɾte]",
      "exampleSentence": "Aquí está mi pasaporte."
    },
    {
      "originalWord": "luggage",
      "translation": "equipaje",
      "transcription": "[ekiˈpaxe]",
      "exampleSentence": "¿Dónde está mi equipaje?"
    },
    {
      "originalWord": "flight",
      "translation": "vuelo",
      "transcription": "[ˈbwelo]",
      "exampleSentence": "Mi vuelo es a las 3 PM."
    },
    {
      "originalWord": "train",
      "translation": "tren",
      "transcription": "[tɾen]",
      "exampleSentence": "Voy en tren."
    },
    {
      "originalWord": "bus",
      "translation": "autobús",
      "transcription": "[awtoˈβus]",
      "exampleSentence": "El autobús ya viene."
    },
    {
      "originalWord": "taxi",
      "translation": "taxi",
      "transcription": "[ˈtaksi]",
      "exampleSentence": "Necesito un taxi, por favor."
    },
    {
      "originalWord": "map",
      "translation": "mapa",
      "transcription": "[ˈmapa]",
      "exampleSentence": "¿Tienes un mapa?"
    },
    {
      "originalWord": "restaurant",
      "translation": "restaurante",
      "transcription": "[restauˈɾante]",
      "exampleSentence": "Vamos a un restaurante."
    },
    {
      "originalWord": "museum",
      "translation": "museo",
      "transcription": "[muˈseo]",
      "exampleSentence": "El museo está cerrado hoy."
    },
    {
      "originalWord": "beach",
      "translation": "playa",
      "transcription": "[ˈplaʝa]",
      "exampleSentence": "¡Me encanta la playa!"
    },
    {
      "originalWord": "reservation",
      "translation": "reserva",
      "transcription": "[reˈseɾβa]",
      "exampleSentence": "Tengo una reserva."
    },
    {
      "originalWord": "entrance",
      "translation": "entrada",
      "transcription": "[enˈtɾaða]",
      "exampleSentence": "¿Dónde está la entrada?"
    },
    {
      "originalWord": "exit",
      "translation": "salida",
      "transcription": "[saˈliða]",
      "exampleSentence": "La salida está allí."
    },
    {
      "originalWord": "emergency",
      "translation": "emergencia",
      "transcription": "[emeɾˈxensja]",
      "exampleSentence": "¡Esto es una emergencia!"
    },
    {
      "originalWord": "pharmacy",
      "translation": "farmacia",
      "transcription": "[faɾˈmasja]",
      "exampleSentence": "Necesito encontrar una farmacia."
    },
    {
      "originalWord": "money",
      "translation": "dinero",
      "transcription": "[diˈneɾo]",
      "exampleSentence": "No tengo dinero."
    },
    {
      "originalWord": "credit card",
      "translation": "tarjeta de crédito",
      "transcription": "[taɾˈxeta ðe ˈkɾeðito]",
      "exampleSentence": "¿Aceptan tarjetas de crédito?"
    }
  ]
}